{
 "1": {
  "name": "JOURNAAL 20 UUR",
  "kijkers": "1.372.000"
 },
 "2": {
  "name": "BESTE ZANGERS",
  "kijkers": "1.188.000"
 },
 "3": {
  "name": "HALF ACHT NIEUWS",
  "kijkers": "1.101.000"
 },
 "4": {
  "name": "EXPEDITIE ROBINSON",
  "kijkers": "1.057.000"
 },
 "5": {
  "name": "DIT WAS HET NIEUWS",
  "kijkers": "980.000"
 },
 "6": {
  "name": "CHATEAU MEILAND",
  "kijkers": "952.000"
 },
 "7": {
  "name": "2 VOOR 12",
  "kijkers": "926.000"
 },
 "8": {
  "name": "JOURNAAL 18 UUR",
  "kijkers": "889.000"
 },
 "9": {
  "name": "EENVANDAAG",
  "kijkers": "725.000"
 },
 "10": {
  "name": "RTL BOULEVARD",
  "kijkers": "721.000"
 },
 "11": {
  "name": "ROOIJAKKERS OVER DE VLOER",
  "kijkers": "717.000"
 },
 "12": {
  "name": "MR FRANK VISSER DOET UITSPRAAK",
  "kijkers": "680.000"
 },
 "13": {
  "name": "OP1",
  "kijkers": "655.000"
 },
 "14": {
  "name": "GOEDE TIJDEN SLECHTE TIJDEN",
  "kijkers": "614.000"
 },
 "15": {
  "name": "EDITIE NL",
  "kijkers": "597.000"
 },
 "16": {
  "name": "SPORTJOURNAAL",
  "kijkers": "586.000"
 },
 "17": {
  "name": "HART VAN NEDERLAND",
  "kijkers": "560.000"
 },
 "18": {
  "name": "NIEUWSUUR",
  "kijkers": "550.000"
 },
 "19": {
  "name": "JINEK",
  "kijkers": "546.000"
 },
 "20": {
  "name": "BINNENSTEBUITEN",
  "kijkers": "456.000"
 },
 "21": {
  "name": "ZES UUR NIEUWS",
  "kijkers": "447.000"
 },
 "22": {
  "name": "JOURNAAL LAAT",
  "kijkers": "431.000"
 },
 "23": {
  "name": "OS PARALYMPICS",
  "kijkers": "414.000"
 },
 "24": {
  "name": "KHALID EN SOPHIE",
  "kijkers": "372.000"
 },
 "25": {
  "name": "ZEMBLA",
  "kijkers": "366.000"
 }
}