{
 "1": {
  "name": "JOURNAAL 20 UUR",
  "kijkers": "2.534.000"
 },
 "2": {
  "name": "CHATEAU MEILAND",
  "kijkers": "1.531.000"
 },
 "3": {
  "name": "RADAR",
  "kijkers": "1.458.000"
 },
 "4": {
  "name": "HALF ACHT NIEUWS",
  "kijkers": "1.409.000"
 },
 "5": {
  "name": "OP1",
  "kijkers": "1.067.000"
 },
 "6": {
  "name": "EENVANDAAG",
  "kijkers": "984.000"
 },
 "7": {
  "name": "JOURNAAL 18 UUR",
  "kijkers": "974.000"
 },
 "8": {
  "name": "UITSTEL VAN EXECUTIE",
  "kijkers": "878.000"
 },
 "9": {
  "name": "RTL BOULEVARD",
  "kijkers": "857.000"
 },
 "10": {
  "name": "VOORAVOND",
  "kijkers": "831.000"
 },
 "11": {
  "name": "BEAU",
  "kijkers": "831.000"
 },
 "12": {
  "name": "GOEDE TIJDEN SLECHTE TIJDEN",
  "kijkers": "800.000"
 },
 "13": {
  "name": "SPORTJOURNAAL",
  "kijkers": "742.000"
 },
 "14": {
  "name": "HART VAN NEDERLAND",
  "kijkers": "727.000"
 },
 "15": {
  "name": "100",
  "kijkers": "718.000"
 },
 "16": {
  "name": "NIEUWSUUR",
  "kijkers": "704.000"
 },
 "17": {
  "name": "EDITIE NL",
  "kijkers": "688.000"
 },
 "18": {
  "name": "BINNENSTEBUITEN",
  "kijkers": "673.000"
 },
 "19": {
  "name": "MET HET MES OP TAFEL",
  "kijkers": "628.000"
 },
 "20": {
  "name": "JOURNAAL LAAT",
  "kijkers": "619.000"
 },
 "21": {
  "name": "VERONICA INSIDE",
  "kijkers": "604.000"
 },
 "22": {
  "name": "ZES UUR NIEUWS",
  "kijkers": "552.000"
 },
 "23": {
  "name": "SHOWNIEUWS",
  "kijkers": "527.000"
 },
 "24": {
  "name": "IK GELOOF IN MIJ",
  "kijkers": "489.000"
 },
 "25": {
  "name": "KAMP WAES",
  "kijkers": "486.000"
 }
}